Metadata-Version: 2.1
Name: chaiprofile
Version: 0.0.1
Summary: Chai Profile by Chai K.
Home-page: https://github.com/CHAI4561/Chaiprofile
Download-URL: https://github.com/CHAI4561/Chaiprofile/archive/v0.0.1.zip
Author: Chai K.
Author-email: francislight66@hotmail.com
License: MIT
Keywords: Profile,Chai,CHAI4561
Classifier: Development Status :: 3 - Alpha
Classifier: Intended Audience :: Education
Classifier: Topic :: Utilities
Classifier: License :: OSI Approved :: MIT License
Classifier: Programming Language :: Python :: 3
Classifier: Programming Language :: Python :: 3.4
Classifier: Programming Language :: Python :: 3.5
Classifier: Programming Language :: Python :: 3.6
Classifier: Programming Language :: Python :: 3.7
Classifier: Programming Language :: Python :: 3.8
Classifier: Programming Language :: Python :: 3.9
Classifier: Programming Language :: Python :: 3.10
License-File: LICENSE.txt
